pillaralgos/__init__.py
pillaralgos/algo1.py
pillaralgos/algo2.py
pillaralgos/algo3_0.py
pillaralgos/algo3_5.py
pillaralgos/algo3_6.py
pillaralgos/algo4.py
pillaralgos/brain.py
pillaralgos/helpers/__init__.py
pillaralgos/helpers/data_handler.py
pillaralgos-1.0.20.dist-info/WHEEL
pillaralgos-1.0.20.dist-info/METADATA
pillaralgos-1.0.20.dist-info/RECORD
