Metadata-Version: 2.1
Name: pillaralgos
Version: 1.0.20
Summary: Algorithms for Pillar. Currently includes "mini" algorithms, nothing too sophisticated.
License: GPL-3.0-or-later
Author: Peter Gates
Author-email: pgate89@gmail.com
Requires-Python: >=3.8,<4.0
Classifier: License :: OSI Approved :: GNU General Public License v3 or later (GPLv3+)
Classifier: Programming Language :: Python :: 3
Classifier: Programming Language :: Python :: 3.8
Classifier: Programming Language :: Python :: 3.9
Requires-Dist: numpy (>=1.20.2,<2.0.0)
Requires-Dist: pandas (>=1.2.3,<2.0.0)
Project-URL: Bug Tracker, https://github.com/pillargg/twitch_chat_analysis/issues
Project-URL: Github, https://github.com/pillargg/twitch_chat_analysis/
Project-URL: Pillar, https://pillar.gg
